aws_sso_cfn_helper/__init__.py
aws_sso_cfn_helper/lookup.py
aws_sso_cfn_helper/template.py
aws_sso_cfn_helper-0.1.0.dist-info/entry_points.txt
aws_sso_cfn_helper-0.1.0.dist-info/WHEEL
aws_sso_cfn_helper-0.1.0.dist-info/METADATA
aws_sso_cfn_helper-0.1.0.dist-info/RECORD
