Metadata-Version: 2.1
Name: aws-sso-cfn-helper
Version: 0.1.0
Summary: Work around current capabilities of AWS SSO CloudFormation resources
Home-page: https://github.com/benkehoe/aws-sso-cfn-helper
License: Apache-2.0
Author: Ben Kehoe
Author-email: ben@kehoe.io
Requires-Python: >=3.5,<4.0
Classifier: License :: OSI Approved :: Apache Software License
Classifier: Programming Language :: Python :: 3
Classifier: Programming Language :: Python :: 3.5
Classifier: Programming Language :: Python :: 3.6
Classifier: Programming Language :: Python :: 3.7
Classifier: Programming Language :: Python :: 3.8
Requires-Dist: boto3 (>=1.14.60,<2.0.0)
Requires-Dist: pyyaml (>=5.3.1,<6.0.0)
